motion_mcp/__init__.py
motion_mcp/config.py
motion_mcp/db.py
motion_mcp/embedding.py
motion_mcp/server.py
motion_mcp-0.1.0.dist-info/METADATA
motion_mcp-0.1.0.dist-info/WHEEL
motion_mcp-0.1.0.dist-info/entry_points.txt
motion_mcp-0.1.0.dist-info/RECORD
