Metadata-Version: 2.4
Name: motion-mcp
Version: 0.1.0
Summary: MCP Server for Motion Database Retrieval - Search motions and get VPD frame data
Requires-Python: >=3.10
Requires-Dist: asyncpg>=0.29.0
Requires-Dist: dashscope>=1.17.0
Requires-Dist: mcp[cli]>=1.0.0
Requires-Dist: numpy>=1.24.0
Requires-Dist: pgvector>=0.3.0
Requires-Dist: python-dotenv>=1.0.0
